libmaths/__init__.py
libmaths/linear.py
libmaths/other.py
libmaths/polynomial.py
libmaths/series.py
libmaths/special.py
libmaths/trig.py
tests/__init__.py
tests/test_libmaths.py
libmaths-0.1.8.dist-info/LICENSE
libmaths-0.1.8.dist-info/METADATA
libmaths-0.1.8.dist-info/WHEEL
libmaths-0.1.8.dist-info/top_level.txt
libmaths-0.1.8.dist-info/RECORD
