Metadata-Version: 2.1
Name: libmaths
Version: 0.1.8
Summary: LibMaths is a Python library created to assist programmers with complex mathematical functions as well as for learning more about Python.
Home-page: https://github.com/Simple2006/libmaths
Author: Vinay Venkatesh
Author-email: vinayven01@gmail.com
License: MIT
Project-URL: Source Code, https://github.com/Simple2006/libmaths
Keywords: Machine Learning,Math,Python
Platform: UNKNOWN
Classifier: Development Status :: 5 - Production/Stable
Classifier: Intended Audience :: Developers
Classifier: Programming Language :: Python :: 3
Classifier: Programming Language :: Python :: 3.6
Classifier: Programming Language :: Python :: 3.7
Classifier: Programming Language :: Python :: 3.8
Classifier: Programming Language :: Python :: 3.9
Classifier: License :: OSI Approved :: MIT License
Requires-Python: >=3
Requires-Dist: numpy
Requires-Dist: sympy
Requires-Dist: matplotlib
